hyperquest/__init__.py
hyperquest/coregistration.py
hyperquest/intrinsic_dimensionality.py
hyperquest/libradtran.py
hyperquest/mlr.cpython-311-darwin.so
hyperquest/optimization.py
hyperquest/radiative_transfer.py
hyperquest/smile.py
hyperquest/snr.py
hyperquest/striping.py
hyperquest/utils.py
hyperquest-0.1.13.dist-info/LICENSE
hyperquest-0.1.13.dist-info/METADATA
hyperquest-0.1.13.dist-info/WHEEL
hyperquest-0.1.13.dist-info/top_level.txt
hyperquest-0.1.13.dist-info/RECORD
