Metadata-Version: 2.1
Name: hyperquest
Version: 0.1.13
Summary: A Python package for Hyperspectral quality estimation in hyperspectral imaging (imaging spectroscopy)
Home-page: https://github.com/brentwilder/hyperquest
Author: Brent Wilder
Author-email: brentwilder@u.boisestate.edu
Classifier: Programming Language :: Python :: 3.8
Classifier: Programming Language :: Python :: 3.9
Classifier: Programming Language :: Python :: 3.10
Classifier: Programming Language :: Python :: 3.11
Classifier: License :: OSI Approved :: MIT License
Classifier: Operating System :: OS Independent
Classifier: Development Status :: 4 - Beta
Classifier: Topic :: Scientific/Engineering
Requires-Python: >=3.8
License-File: LICENSE
Requires-Dist: numpy<2.0.0
Requires-Dist: pandas>=1.2.0
Requires-Dist: scikit-image>=0.18.0
Requires-Dist: scikit-learn>=0.24.0
Requires-Dist: joblib>=1.0.0
Requires-Dist: cython>=3.0.11
Requires-Dist: spectral>=0.23.0
Requires-Dist: pysolar>=0.13
Requires-Dist: h5netcdf>=1.1.0
